<?xml version="1.0" encoding="utf-8"?>
<TextureAtlas imagePath="sl-a0.png">
	<!-- Created with Adobe Animate version 20.0.0.17400 -->
	<!-- http://www.adobe.com/products/animate.html -->
	<SubTexture name="sl-a0 Sing Note DOWN0001" x="36" y="1624" width="355" height="346" frameX="0" frameY="10" frameWidth="560" frameHeight="551"/>
	<SubTexture name="sl-a0 Sing Note DOWN0001" x="412" y="1595" width="378" height="377" frameX="0" frameY="10" frameWidth="583" frameHeight="582"/>
	<SubTexture name="sl-a0 Sing Note DOWN0001" x="412" y="1595" width="378" height="377" frameX="0" frameY="10" frameWidth="583" frameHeight="582"/>
	<SubTexture name="sl-a0 Sing Note DOWN0001" x="412" y="1595" width="378" height="377" frameX="0" frameY="10" frameWidth="583" frameHeight="582"/>
	<SubTexture name="sl-a0 Sing Note DOWN0001" x="412" y="1595" width="378" height="377" frameX="0" frameY="10" frameWidth="583" frameHeight="582"/>
	<SubTexture name="sl-a0 Sing Note DOWN0001" x="412" y="1595" width="378" height="377" frameX="0" frameY="10" frameWidth="583" frameHeight="582"/>
	<SubTexture name="sl-a0 Sing Note DOWN0001" x="412" y="1595" width="378" height="377" frameX="0" frameY="10" frameWidth="583" frameHeight="582"/>
	<SubTexture name="sl-a0 Sing Note LEFT0000" x="14" y="385" width="311" height="345" frameX="0" frameY="10" frameWidth="516" frameHeight="550"/>
	<SubTexture name="sl-a0 Sing Note RIGHT0000" x="31" y="768" width="312" height="346" frameX="0" frameY="10" frameWidth="517" frameHeight="551"/>
	<SubTexture name="sl-a0 Sing Note UP0001" x="21" y="1170" width="356" height="342" frameX="0" frameY="10" frameWidth="561" frameHeight="547"/>
	<SubTexture name="sl-a0 Sing Note UP0001" x="414" y="1160" width="379" height="376" frameX="0" frameY="10" frameWidth="584" frameHeight="581"/>
	<SubTexture name="sl-a0 Sing Note UP0001" x="414" y="1160" width="379" height="376" frameX="0" frameY="10" frameWidth="584" frameHeight="581"/>
	<SubTexture name="sl-a0 Sing Note UP0001" x="414" y="1160" width="379" height="376" frameX="0" frameY="10" frameWidth="584" frameHeight="581"/>
	<SubTexture name="sl-a0 Sing Note UP0001" x="414" y="1160" width="379" height="376" frameX="0" frameY="10" frameWidth="584" frameHeight="581"/>
	<SubTexture name="sl-a0 Sing Note UP0001" x="414" y="1160" width="379" height="376" frameX="0" frameY="10" frameWidth="584" frameHeight="581"/>
	<SubTexture name="sl-a0 Sing Note UP0001" x="414" y="1160" width="379" height="376" frameX="0" frameY="10" frameWidth="584" frameHeight="581"/>
	<SubTexture name="sl-a0 idle dance0000" x="4" y="0" width="320" height="353" frameX="0" frameY="10" frameWidth="525" frameHeight="558"/>
</TextureAtlas>
